residuecontact/__init__.py
residuecontact/residuecontact.py
residuecontact-0.0.5.dist-info/LICENSE
residuecontact-0.0.5.dist-info/METADATA
residuecontact-0.0.5.dist-info/WHEEL
residuecontact-0.0.5.dist-info/top_level.txt
residuecontact-0.0.5.dist-info/RECORD
