Metadata-Version: 2.1
Name: residuecontact
Version: 0.0.5
Summary: A utility package to generate 3D residue distance graph
Home-page: https://github.com/aldenleung/residuecontact/
Author: Alden Leung
Author-email: alden.leung@gmail.com
Classifier: Programming Language :: Python :: 3.7
Classifier: Programming Language :: Python :: 3.8
Classifier: Programming Language :: Python :: 3.9
Classifier: Programming Language :: Python :: 3.10
Classifier: Programming Language :: Python :: 3.11
Classifier: License :: OSI Approved :: GNU General Public License v3 (GPLv3)
License-File: LICENSE
Requires-Dist: biopython (>=1.80)
Requires-Dist: networkx (>=2.8.8)
Requires-Dist: scipy (>=1.9.3)
Requires-Dist: biodata (>=0.0.6)
